README.md
setup.py
pandas_units_extension/__init__.py
pandas_units_extension/units.py
pandas_units_extension/version.py
pandas_units_extension.egg-info/PKG-INFO
pandas_units_extension.egg-info/SOURCES.txt
pandas_units_extension.egg-info/dependency_links.txt
pandas_units_extension.egg-info/requires.txt
pandas_units_extension.egg-info/top_level.txt
tests/__init__.py
tests/test_pandas_units_extension.py