Metadata-Version: 2.1
Name: pandas-units-extension
Version: 0.1.0
Summary: Extension pandas dtype and array for physical units.
Home-page: https://github.com/janpipek/pandas-units-extension
Author: Jan Pipek
Author-email: jan.pipek@gmail.com
License: MIT
Platform: UNKNOWN
Requires-Python: >=3.6
